AUTHORS
LICENSE
MANIFEST.in
README.rst
setup.cfg
setup.py
dj_dynamic_forms.egg-info/PKG-INFO
dj_dynamic_forms.egg-info/SOURCES.txt
dj_dynamic_forms.egg-info/dependency_links.txt
dj_dynamic_forms.egg-info/not-zip-safe
dj_dynamic_forms.egg-info/requires.txt
dj_dynamic_forms.egg-info/top_level.txt
docs/Makefile
docs/make.bat
docs/source/changes.rst
docs/source/conf.py
docs/source/index.rst
docs/source/installation.rst
docs/source/problems.rst
docs/source/usage.rst
docs/source/ref/actions.rst
docs/source/ref/admin.rst
docs/source/ref/fields.rst
docs/source/ref/formfields.rst
docs/source/ref/forms.rst
docs/source/ref/index.rst
docs/source/ref/middlewares.rst
docs/source/ref/models.rst
docs/source/ref/views.rst
dynamic_forms/__init__.py
dynamic_forms/actions.py
dynamic_forms/admin.py
dynamic_forms/conf.py
dynamic_forms/fields.py
dynamic_forms/formfields.py
dynamic_forms/forms.py
dynamic_forms/middlewares.py
dynamic_forms/models.py
dynamic_forms/views.py
dynamic_forms/locale/de/LC_MESSAGES/django.mo
dynamic_forms/locale/de/LC_MESSAGES/django.po
dynamic_forms/locale/en/LC_MESSAGES/django.mo
dynamic_forms/locale/en/LC_MESSAGES/django.po
dynamic_forms/migrations/0001_initial.py
dynamic_forms/migrations/__init__.py
dynamic_forms/templates/dynamic_forms/email.txt
dynamic_forms/templates/dynamic_forms/form.html
dynamic_forms/templates/dynamic_forms/form_success.html
example/example.db
example/manage.py
example/example/__init__.py
example/example/settings.py
example/example/urls.py
example/example/wsgi.py
tests/__init__.py
tests/models.py
tests/requirements.txt
tests/settings.py
tests/test_actions.py
tests/test_admin.py
tests/test_formfields.py
tests/test_forms.py
tests/test_models.py
tests/test_views.py
tests/urls.py
tests/views.py
tests/templates/404.html