Metadata-Version: 1.1
Name: dj-dynamic-forms
Version: 0.4
Summary: Dynamic forms for Django - data storage in Postgres Hstore. It is a reusable Django application to create and configure forms through the admin.
Home-page: http://github.com/chhantyal/dj-dynamic-forms
Author: Nar Kumar Chhantyal
Author-email: nkchhantyal@gmail.com
License: BSD
Platform: UNKNOWN
Classifier: Development Status :: 3 - Alpha
Classifier: Environment :: Web Environment
Classifier: Intended Audience :: Developers
Classifier: License :: OSI Approved :: BSD License
Classifier: Operating System :: OS Independent
Classifier: Programming Language :: Python
Classifier: Programming Language :: Python :: 2
Classifier: Programming Language :: Python :: 2.6
Classifier: Programming Language :: Python :: 2.7
Classifier: Programming Language :: Python :: 3
Classifier: Programming Language :: Python :: 3.2
Classifier: Programming Language :: Python :: 3.3
Classifier: Framework :: Django
